aiida_plugin_template/__init__.py
aiida_plugin_template/code.py
aiida_plugin_template/calculations/__init__.py
aiida_plugin_template/calculations/multiply.py
aiida_plugin_template/data/__init__.py
aiida_plugin_template/data/data_cli.py
aiida_plugin_template/data/multiply.py
aiida_plugin_template/parsers/__init__.py
aiida_plugin_template/parsers/multiply.py
aiida_plugin_template/tests/__init__.py
aiida_plugin_template/tests/test_calculations.py
aiida_plugin_template/workflows/__init__.py
aiida_plugin_template-0.2.0.data/scripts/cli.py
aiida_plugin_template-0.2.0.dist-info/DESCRIPTION.rst
aiida_plugin_template-0.2.0.dist-info/METADATA
aiida_plugin_template-0.2.0.dist-info/RECORD
aiida_plugin_template-0.2.0.dist-info/WHEEL
aiida_plugin_template-0.2.0.dist-info/entry_points.txt
aiida_plugin_template-0.2.0.dist-info/metadata.json
aiida_plugin_template-0.2.0.dist-info/top_level.txt
