Metadata-Version: 2.0
Name: aiida-plugin-template
Version: 0.2.0
Summary: AiiDA plugin template for testing and getting started with development
Home-page: https://github.com/aiidateam/aiida-plugin-template
Author: Rico Haeuselmann, Leopold Talirz
Author-email: haeuselm@epfl.ch
License: Creative Commons
Platform: UNKNOWN
Classifier: Programming Language :: Python
Requires-Dist: aiida (>=0.11.0)
Provides-Extra: pre-commit
Requires-Dist: pre-commit; extra == 'pre-commit'
Requires-Dist: prospector; extra == 'pre-commit'
Requires-Dist: pylint; extra == 'pre-commit'
Requires-Dist: yapf; extra == 'pre-commit'
Provides-Extra: testing
Requires-Dist: aiida-core[testing]; extra == 'testing'
